symphysics/__init__.py
symphysics/sprites.py
symphysics/symsystem.py
symphysics-0.1.0.dist-info/LICENSE
symphysics-0.1.0.dist-info/METADATA
symphysics-0.1.0.dist-info/WHEEL
symphysics-0.1.0.dist-info/top_level.txt
symphysics-0.1.0.dist-info/RECORD
