Metadata-Version: 2.1
Name: symphysics
Version: 0.1.0
Summary: The symphysics library for creating physics simulations using python and sympy
Home-page: https://github.com/rjbourne/symphysics/
Author: Robert B., Zeph B.
Author-email: symphysics@gmail.com
License: MIT
Platform: UNKNOWN
Classifier: License :: OSI Approved :: MIT License
Classifier: Programming Language :: Python :: 3
Classifier: Programming Language :: Python :: 3.7
Requires-Python: >=3.5
Requires-Dist: sympy
Requires-Dist: numpy
Requires-Dist: scipy
Requires-Dist: dill
Requires-Dist: matplotlib
